MANIFEST.in
README.rst
setup.cfg
setup.py
blender26-meshio/__init__.py
blender26-meshio/bl.py
blender26-meshio/export_mqo.py
blender26-meshio/export_pmd.py
blender26-meshio/export_pmx.py
blender26-meshio/import_mqo.py
blender26-meshio/import_pmd.py
blender26-meshio/import_pmx.py
blender26-meshio/exporter/__init__.py
blender26-meshio/exporter/bonebuilder.py
blender26-meshio/exporter/oneskinmesh.py
blender26-meshio/exporter/vertexarray.py
blender26-meshio/pymeshio/__init__.py
blender26-meshio/pymeshio/common.py
blender26-meshio/pymeshio/converter.py
blender26-meshio/pymeshio/englishmap.py
blender26-meshio/pymeshio/main.py
blender26-meshio/pymeshio/vpd.py
blender26-meshio/pymeshio/mqo/__init__.py
blender26-meshio/pymeshio/mqo/reader.py
blender26-meshio/pymeshio/obj/__init__.py
blender26-meshio/pymeshio/obj/reader.py
blender26-meshio/pymeshio/pmd/__init__.py
blender26-meshio/pymeshio/pmd/reader.py
blender26-meshio/pymeshio/pmd/writer.py
blender26-meshio/pymeshio/pmm/__init__.py
blender26-meshio/pymeshio/pmm/reader.py
blender26-meshio/pymeshio/pmx/__init__.py
blender26-meshio/pymeshio/pmx/reader.py
blender26-meshio/pymeshio/pmx/writer.py
blender26-meshio/pymeshio/vmd/__init__.py
blender26-meshio/pymeshio/vmd/reader.py
blender26-meshio/pymeshio/vmd/writer.py
blender26-meshio/pymeshio/x/__init__.py
blender26-meshio/pymeshio/x/reader.py
blender26-meshio/pymeshio/x/writer.py
pymeshio/__init__.py
pymeshio/common.py
pymeshio/converter.py
pymeshio/englishmap.py
pymeshio/main.py
pymeshio/vpd.py
pymeshio.egg-info/PKG-INFO
pymeshio.egg-info/SOURCES.txt
pymeshio.egg-info/dependency_links.txt
pymeshio.egg-info/entry_points.txt
pymeshio.egg-info/top_level.txt
pymeshio.egg-info/zip-safe
pymeshio/mqo/__init__.py
pymeshio/mqo/reader.py
pymeshio/obj/__init__.py
pymeshio/obj/reader.py
pymeshio/pmd/__init__.py
pymeshio/pmd/reader.py
pymeshio/pmd/writer.py
pymeshio/pmm/__init__.py
pymeshio/pmm/reader.py
pymeshio/pmx/__init__.py
pymeshio/pmx/reader.py
pymeshio/pmx/writer.py
pymeshio/vmd/__init__.py
pymeshio/vmd/reader.py
pymeshio/vmd/writer.py
pymeshio/x/__init__.py
pymeshio/x/reader.py
pymeshio/x/writer.py