Metadata-Version: 1.1
Name: pymeshio
Version: 2.7.13
Summary: 3d model io library for mqo, pmd, pmx, vmd and vpd
Home-page: https://pypi.python.org/pypi/pymeshio/
Author: ousttrue
Author-email: ousttrue@gmail.com
License: zlib
Keywords: mqo,pmd,pmx,vmd,vpd,mmd,blender
Platform: UNKNOWN
Classifier: Programming Language :: Python :: 3
Classifier: License :: OSI Approved :: zlib/libpng License
Classifier: Topic :: Multimedia :: Graphics :: 3D Modeling
